syncopy/__init__.py
syncopy/__main__.py
syncopy/settings.py
syncopy/sync.py
syncopy/util.py
syncopy-0.1.3.dist-info/METADATA
syncopy-0.1.3.dist-info/WHEEL
syncopy-0.1.3.dist-info/entry_points.txt
syncopy-0.1.3.dist-info/top_level.txt
syncopy-0.1.3.dist-info/zip-safe
syncopy-0.1.3.dist-info/RECORD
