Metadata-Version: 2.1
Name: syncopy
Version: 0.1.3
Summary: syncopydeep-copies one directory to another
Home-page: http://bitbucket.org/neogeny/syncopy
Author: Juancarlo Añez
Author-email: apalala@gmail.com
License: BSD License
Platform: UNKNOWN
Classifier: Development Status :: 5 - Production/Stable
Classifier: License :: OSI Approved :: BSD License
Classifier: Natural Language :: English
Classifier: Intended Audience :: Developers
Classifier: Intended Audience :: System Administrators
Classifier: Environment :: Console
Classifier: Operating System :: OS Independent
Classifier: Programming Language :: Python :: 3.8
Classifier: Topic :: Utilities
Requires: docopt
